marmel_grammar/__init__.py
marmel_grammar/dataset.py
marmel_grammar/grammar.py
marmel_grammar-0.1.9.dist-info/METADATA
marmel_grammar-0.1.9.dist-info/WHEEL
marmel_grammar-0.1.9.dist-info/top_level.txt
marmel_grammar-0.1.9.dist-info/RECORD
