Metadata-Version: 2.4
Name: marmel-grammar
Version: 0.1.9
Summary: Библиотека русской морфологии и транслитерации для Python
Home-page: https://t.me/dev_marmel
Author: Dev-Marmel
Author-email: marmelgpt@gmail.com
Project-URL: Bug Reports, https://t.me/dev_marmel
Project-URL: Source, https://t.me/dev_marmel
Project-URL: Documentation, https://t.me/dev_marmel
Project-URL: Telegram, https://t.me/dev_marmel
Keywords: russian,morphology,declension,grammar,transliteration,names,verbs,linguistic
Classifier: Development Status :: 4 - Beta
Classifier: Intended Audience :: Developers
Classifier: Operating System :: OS Independent
Classifier: Programming Language :: Python :: 3
Classifier: Programming Language :: Python :: 3.8
Classifier: Programming Language :: Python :: 3.9
Classifier: Programming Language :: Python :: 3.10
Classifier: Programming Language :: Python :: 3.11
Classifier: Programming Language :: Python :: 3.12
Classifier: Topic :: Software Development :: Libraries :: Python Modules
Classifier: Topic :: Text Processing :: Linguistic
Classifier: Natural Language :: Russian
Requires-Python: >=3.8
Provides-Extra: dev
Requires-Dist: pytest>=6.0; extra == "dev"
Requires-Dist: black; extra == "dev"
Requires-Dist: isort; extra == "dev"
Provides-Extra: telegram
Requires-Dist: python-telegram-bot>=20.7; extra == "telegram"
Dynamic: author
Dynamic: author-email
Dynamic: classifier
Dynamic: description
Dynamic: description-content-type
Dynamic: home-page
Dynamic: keywords
Dynamic: project-url
Dynamic: provides-extra
Dynamic: requires-python
Dynamic: summary
